locust_victoria_metrics/__init__.py
locust_victoria_metrics/pusher.py
locust_victoria_metrics-0.0.3.dist-info/licenses/LICENSE
locust_victoria_metrics-0.0.3.dist-info/METADATA
locust_victoria_metrics-0.0.3.dist-info/WHEEL
locust_victoria_metrics-0.0.3.dist-info/top_level.txt
locust_victoria_metrics-0.0.3.dist-info/RECORD
