Metadata-Version: 2.4
Name: locust-victoria-metrics
Version: 0.0.3
Summary: A Locust plugin to extract test results and push metrics to Victoria Metrics
Home-page: https://github.com/dsetiawan230294/locust-victoria-metrics
Author: Didit Setiawan
Author-email: Didit Setiawan <didit@pintu.co.id>
License: MIT
Project-URL: Homepage, https://github.com/dsetiawan230294/locust-victoria-metrics
Project-URL: Bug Tracker, https://github.com/dsetiawan230294/locust-victoria-metrics/issues
Keywords: locust,loadtest,metrics,victoria-metrics,locust-plugin
Classifier: Programming Language :: Python :: 3.10
Classifier: License :: OSI Approved :: MIT License
Classifier: Operating System :: OS Independent
Requires-Python: >=3.10
License-File: LICENSE
Requires-Dist: locust==2.29.1
Dynamic: author
Dynamic: home-page
Dynamic: license-file
Dynamic: requires-python
